SBMate/__init__.py
SBMate/constants.py
SBMate/dag_analyzer.py
SBMate/metric_calculator.py
SBMate/sbmate.py
SBMate/sbml_annotation.py
SBMate/uniprot_kegg_analyzer.py
SBMate/knowledge_resources/chebi_graph.gpickle
SBMate/knowledge_resources/go_graph.gpickle
SBMate/knowledge_resources/sbo_graph.gpickle
SBMate-1.1.3.dist-info/LICENSE
SBMate-1.1.3.dist-info/METADATA
SBMate-1.1.3.dist-info/WHEEL
SBMate-1.1.3.dist-info/top_level.txt
SBMate-1.1.3.dist-info/RECORD
