Metadata-Version: 2.1
Name: SBMate
Version: 1.1.3
Summary: Annotation quality metrics calculator (coverage, consistency, specificity).
Home-page: https://github.com/woosubs/SBMate
Author: Woosub Shin, Joseph L. Hellerstein
Author-email: woosubs@umich.edu
License: UNKNOWN
Platform: UNKNOWN
Classifier: Development Status :: 3 - Alpha
Classifier: Intended Audience :: Developers
Classifier: Topic :: Scientific/Engineering :: Bio-Informatics
Classifier: License :: OSI Approved :: MIT License
Classifier: Programming Language :: Python :: 3.8
Classifier: Programming Language :: Python :: 3.9
License-File: LICENSE
Requires-Dist: coverage (==5.5)
Requires-Dist: coveralls
Requires-Dist: networkx
Requires-Dist: nose
Requires-Dist: numpy
Requires-Dist: pandas
Requires-Dist: pickle5
Requires-Dist: python-libsbml
Requires-Dist: pyyaml
Requires-Dist: requests
